fsfr/cmr.py
fsfr/discretiser.py
fsfr/dominion.py
fsfr/fsfr.py
fsfr/ga_a.py
fsfr/ga_bc.py
fsfr/gpso_a.py
fsfr/gpso_bc.py
fsfr/mifsnd.py
fsfr/mrmr.py
fsfr/mutate.py
fsfr/mutual_information.py
fsfr/pinitialise.py
fsfr/preprocessing.py
fsfr/reldep.py
fsfr/rsm_a.py
fsfr/rsm_b.py
fsfr/rsm_c.py
fsfr/svc.py
fsfr/tpmbx.py
Feature_Selction_Ranking_Algorithms-1.0.7.dist-info/LICENSE
Feature_Selction_Ranking_Algorithms-1.0.7.dist-info/METADATA
Feature_Selction_Ranking_Algorithms-1.0.7.dist-info/WHEEL
Feature_Selction_Ranking_Algorithms-1.0.7.dist-info/top_level.txt
Feature_Selction_Ranking_Algorithms-1.0.7.dist-info/RECORD
