Metadata-Version: 2.1
Name: Feature-Selction-Ranking-Algorithms
Version: 1.0.7
Summary: A Feature Selection and Feature ranking Package that can be used to select and rank features in datasets
Home-page: UNKNOWN
Author: Lakshajyoti Paul
Author-email: lakshajyotipaul777@gmail.com
License: MIT
Platform: UNKNOWN
Classifier: Programming Language :: Python :: 3.7
Classifier: License :: OSI Approved :: MIT License
Classifier: Operating System :: OS Independent
